whitebox_plugin_videojs/pyproject.toml
whitebox_plugin_videojs/__init__.py
whitebox_plugin_videojs/external-asset-manifest.json
whitebox_plugin_videojs/jsx/VideoJS.jsx
whitebox_plugin_videojs/static/whitebox_plugin_videojs/whep-tech.js
whitebox_plugin_videojs/whitebox_plugin_videojs.py
whitebox_test_plugin_videojs/__init__.py
whitebox_test_plugin_videojs/test_whitebox_plugin_template.py
whitebox_plugin_videojs-0.1.3.dist-info/LICENSE
whitebox_plugin_videojs-0.1.3.dist-info/METADATA
whitebox_plugin_videojs-0.1.3.dist-info/WHEEL
whitebox_plugin_videojs-0.1.3.dist-info/RECORD
